{"title":"PHiSH 1994-05-07 Dallas, TX (Live Phish Volume 18) [FLAC]","uid":11974095,"size":1242216450,"categoryP":"audio","categoryS":"flac","magnet":"?xt=urn:btih:00343a900750fa04bb3aa60034781b8263b083df&amp;dn=PHiSH+1994-05-07+Dallas%2C+TX+%28Live+Phish+Volume+18%29+%5BFLAC%5D&amp;tr=udp%3A%2F%2Ftracker.openbittorrent.com%3A80&amp;tr=udp%3A%2F%2Fopen.demonii.com%3A1337&amp;tr=udp%3A%2F%2Ftracker.coppersurfer.tk%3A6969&amp;tr=udp%3A%2F%2Fexodus.desync.com%3A6969","seeders":1,"leechers":0,"uploader":"sailorsaint","files":28,"time":1432960629,"description":"PHiSH\n1994-05-07\nThe Bomb Factory\nDallas, TX \n\n------------------------------\nSBD\nLive Phish Volume 18\n\nRecorded to two-track DAT by Paul Languedoc\nPost-Production: Phish Archives\nMastered by Adam Ayan at Gateway Mastering\nPhish Archivist: Kevin Shapiro, assisted by Rob O'Dea and Kevin Monty\n------------------------------\n\nDISC ONE \t\nSET ONE\n01 \tLlama (5:01) \t \n02 \tHorn (4:30) \t \n03 \tDivided Sky (14:55) \t\n04 \tMound (5:53) \t \n05 \tFast Enough for You (6:32) \t \n06 \tScent of a Mule (7:01) \t \n07 \tSplit Open and Melt (13:59) \t\n08 \tIf I Could (5:50) \t \n09 \tSuzy Greenberg (6:19) \t \n\t\nDISC TWO \t\nSET TWO\n01 \tLoving Cup (6:32) \t \n02 \tSparkle (3:35) \t \n03 \tTweezer -&gt; (25:59) \t\n04 \tSparks -&gt; (2:41) \t \n05 \tMakisupa Policeman -&gt; (2:27) \t \n06 \tTweezer -&gt; (7:29) \t \n07 \tWalk Away -&gt; (4:04) \t \n08 \tTweezer -&gt; (7:25)  \n09 \tCannonball -&gt; (2:06) \t \n10 \tPurple Rain -&gt; (6:30) \t \n11 \tDallas Jam -&gt; (5:20) \t \n12 \tTweezer Reprise (4:30) \t \n\nDISC THREE \t\nENCORE\n01 \tAmazing Grace (2:03) \t \n02 \tSample in a Jar (5:23) \t \nFILLER (1994-11-22)\n03\tFunky Bitch -&gt; (6:41) \t \n04 \tColumbia Jam -&gt; (22:07) \t\n05 \tJerusalem Jerusalem (2:06)","torrent":{"xt":"urn:btih:00343a900750fa04bb3aa60034781b8263b083df","amp;dn":"PHiSH+1994-05-07+Dallas%2C+TX+%28Live+Phish+Volume+18%29+%5BFLAC%5D","amp;tr":["udp%3A%2F%2Ftracker.openbittorrent.com%3A80","udp%3A%2F%2Fopen.demonii.com%3A1337","udp%3A%2F%2Ftracker.coppersurfer.tk%3A6969","udp%3A%2F%2Fexodus.desync.com%3A6969"],"infoHash":"00343a900750fa04bb3aa60034781b8263b083df","infoHashBuffer":{"type":"Buffer","data":[0,52,58,144,7,80,250,4,187,58,166,0,52,120,27,130,99,176,131,223]},"announce":[],"urlList":[]}}