{"title":"The Giver 2014 WEBrip 480p XVID AC3 ACAB","uid":11017938,"size":1628006152,"categoryP":"video","categoryS":"movies","magnet":"?xt=urn:btih:064c6542a7c957650ef3f0f7a65a571a59e442a8&amp;dn=The+Giver+2014+WEBrip+480p+XVID+AC3+ACAB&amp;tr=udp%3A%2F%2Ftracker.openbittorrent.com%3A80&amp;tr=udp%3A%2F%2Fopen.demonii.com%3A1337&amp;tr=udp%3A%2F%2Ftracker.coppersurfer.tk%3A6969&amp;tr=udp%3A%2F%2Fexodus.desync.com%3A6969","seeders":1,"leechers":0,"uploader":"TvTeam","files":4,"time":1410533562,"description":" &lt;a href=&quot;http://www.torrenting.com&quot; rel=&quot;nofollow&quot; target=&quot;_NEW&quot;&gt;http://www.torrenting.com&lt;/a&gt;\n\nSign up is OPEN - for time being. Come and have fun.","torrent":{"xt":"urn:btih:064c6542a7c957650ef3f0f7a65a571a59e442a8","amp;dn":"The+Giver+2014+WEBrip+480p+XVID+AC3+ACAB","amp;tr":["udp%3A%2F%2Ftracker.openbittorrent.com%3A80","udp%3A%2F%2Fopen.demonii.com%3A1337","udp%3A%2F%2Ftracker.coppersurfer.tk%3A6969","udp%3A%2F%2Fexodus.desync.com%3A6969"],"infoHash":"064c6542a7c957650ef3f0f7a65a571a59e442a8","infoHashBuffer":{"type":"Buffer","data":[6,76,101,66,167,201,87,101,14,243,240,247,166,90,87,26,89,228,66,168]},"announce":[],"urlList":[]}}