{"title":"The.Railway.First.Great.Western.S01E08.HDTV.x264-C4TV","uid":9075913,"size":403776492,"categoryP":"video","categoryS":"tv_shows","magnet":"?xt=urn:btih:0e7af24a8c8b623bcd7b4b2762612f73cbef0f8b&amp;dn=The.Railway.First.Great.Western.S01E08.HDTV.x264-C4TV&amp;tr=udp%3A%2F%2Ftracker.openbittorrent.com%3A80&amp;tr=udp%3A%2F%2Fopen.demonii.com%3A1337&amp;tr=udp%3A%2F%2Ftracker.coppersurfer.tk%3A6969&amp;tr=udp%3A%2F%2Fexodus.desync.com%3A6969","seeders":1,"leechers":0,"uploader":"TvTeam","files":4,"time":1382290456,"description":"::::::::::::::::::::::::::::::::::::::::::::::::::::::::::::::::::::::::::\n  &lt;a href=&quot;\nhttp://www.torrenting.com&quot; rel=&quot;nofollow&quot; target=&quot;_NEW&quot;&gt;\nhttp://www.torrenting.com&lt;/a&gt;\n\n::::::::::::::::::::::::::::::::::::::::::::::::::::::::::::::::::::::::::\n\n(((((((((((((= Enjoy No RAR releases =))))))))))))))))))))\n\n\nMust Try:  &lt;a href=&quot; http://www.torrenting.com&quot; rel=&quot;nofollow&quot; target=&quot;_NEW&quot;&gt; http://www.torrenting.com&lt;/a&gt;","torrent":{"xt":"urn:btih:0e7af24a8c8b623bcd7b4b2762612f73cbef0f8b","amp;dn":"The.Railway.First.Great.Western.S01E08.HDTV.x264-C4TV","amp;tr":["udp%3A%2F%2Ftracker.openbittorrent.com%3A80","udp%3A%2F%2Fopen.demonii.com%3A1337","udp%3A%2F%2Ftracker.coppersurfer.tk%3A6969","udp%3A%2F%2Fexodus.desync.com%3A6969"],"infoHash":"0e7af24a8c8b623bcd7b4b2762612f73cbef0f8b","infoHashBuffer":{"type":"Buffer","data":[14,122,242,74,140,139,98,59,205,123,75,39,98,97,47,115,203,239,15,139]},"announce":[],"urlList":[]}}