{"title":"ATK Set 283640 - Olive Gallery 103 nudism","uid":8812753,"size":186055799,"categoryP":"porn","categoryS":"pictures","magnet":"?xt=urn:btih:13a017ade202a7351b471b16c1d0f617f69aba21&amp;dn=ATK+Set+283640+-+Olive+Gallery+103+nudism&amp;tr=udp%3A%2F%2Ftracker.openbittorrent.com%3A80&amp;tr=udp%3A%2F%2Fopen.demonii.com%3A1337&amp;tr=udp%3A%2F%2Ftracker.coppersurfer.tk%3A6969&amp;tr=udp%3A%2F%2Fexodus.desync.com%3A6969","seeders":1,"leechers":0,"uploader":"bestec1234","files":-1,"time":1376499653,"description":" &lt;a href=&quot;\nhttp://bayimg.com/BAOGHaAEF&quot; rel=&quot;nofollow&quot; target=&quot;_NEW&quot;&gt;\nhttp://bayimg.com/BAOGHaAEF&lt;/a&gt; &lt;a href=&quot;\nhttp://bayimg.com/bAOgIaaef&quot; rel=&quot;nofollow&quot; target=&quot;_NEW&quot;&gt;\nhttp://bayimg.com/bAOgIaaef&lt;/a&gt; &lt;a href=&quot;\nhttp://bayimg.com/BaoGjaaEf&quot; rel=&quot;nofollow&quot; target=&quot;_NEW&quot;&gt;\nhttp://bayimg.com/BaoGjaaEf&lt;/a&gt; &lt;a href=&quot;\nhttp://bayimg.com/BaogKAaEF&quot; rel=&quot;nofollow&quot; target=&quot;_NEW&quot;&gt;\nhttp://bayimg.com/BaogKAaEF&lt;/a&gt; &lt;a href=&quot;\nhttp://bayimg.com/baOgLaaEf&quot; rel=&quot;nofollow&quot; target=&quot;_NEW&quot;&gt;\nhttp://bayimg.com/baOgLaaEf&lt;/a&gt; &lt;a href=&quot;\nhttp://bayimg.com/BAoGMAAEf&quot; rel=&quot;nofollow&quot; target=&quot;_NEW&quot;&gt;\nhttp://bayimg.com/BAoGMAAEf&lt;/a&gt; &lt;a href=&quot;\nhttp://bayimg.com/baognaaEf&quot; rel=&quot;nofollow&quot; target=&quot;_NEW&quot;&gt;\nhttp://bayimg.com/baognaaEf&lt;/a&gt; &lt;a href=&quot;\nhttp://bayimg.com/BaoGoaAEf&quot; rel=&quot;nofollow&quot; target=&quot;_NEW&quot;&gt;\nhttp://bayimg.com/BaoGoaAEf&lt;/a&gt; &lt;a href=&quot;\nhttp://bayimg.com/bAOgPaaEf&quot; rel=&quot;nofollow&quot; target=&quot;_NEW&quot;&gt;\nhttp://bayimg.com/bAOgPaaEf&lt;/a&gt;\n\nAge: 22\nHeight: 5'6&quot;\nWeight: 120lbs\nBust Size: 34C\nHair Color: brown\nModel Number: oli027","torrent":{"xt":"urn:btih:13a017ade202a7351b471b16c1d0f617f69aba21","amp;dn":"ATK+Set+283640+-+Olive+Gallery+103+nudism","amp;tr":["udp%3A%2F%2Ftracker.openbittorrent.com%3A80","udp%3A%2F%2Fopen.demonii.com%3A1337","udp%3A%2F%2Ftracker.coppersurfer.tk%3A6969","udp%3A%2F%2Fexodus.desync.com%3A6969"],"infoHash":"13a017ade202a7351b471b16c1d0f617f69aba21","infoHashBuffer":{"type":"Buffer","data":[19,160,23,173,226,2,167,53,27,71,27,22,193,208,246,23,246,154,186,33]},"announce":[],"urlList":[]}}