{"title":"We Fuck Black Girls – Jenna Foxx","uid":15865034,"size":352438117,"categoryP":"porn","categoryS":"movie_clips","magnet":"?xt=urn:btih:4371f22e0af7cde2435975bbbd5219b6b4340b08&amp;dn=We+Fuck+Black+Girls+%26ndash%3B+Jenna+Foxx&amp;tr=udp%3A%2F%2Ftracker.leechers-paradise.org%3A6969&amp;tr=udp%3A%2F%2Fzer0day.ch%3A1337&amp;tr=udp%3A%2F%2Fopen.demonii.com%3A1337&amp;tr=udp%3A%2F%2Ftracker.coppersurfer.tk%3A6969&amp;tr=udp%3A%2F%2Fexodus.desync.com%3A6969","seeders":1,"leechers":2,"uploader":"hunter534","files":1,"time":1474358940,"description":"Size: 336.11 MiB\r\nDuration: 00:29:52\r\nFormat: MP4\r\n\r\n\r\ncover+sceenshot:\r\n \nhttp://img-one.com/img-57e0d2770164e.html \r\n \nhttp://img-one.com/img-57e0d2802a5b9.html","torrent":{"xt":"urn:btih:4371f22e0af7cde2435975bbbd5219b6b4340b08","amp;dn":"We+Fuck+Black+Girls+%26ndash%3B+Jenna+Foxx","amp;tr":["udp%3A%2F%2Ftracker.leechers-paradise.org%3A6969","udp%3A%2F%2Fzer0day.ch%3A1337","udp%3A%2F%2Fopen.demonii.com%3A1337","udp%3A%2F%2Ftracker.coppersurfer.tk%3A6969","udp%3A%2F%2Fexodus.desync.com%3A6969"],"infoHash":"4371f22e0af7cde2435975bbbd5219b6b4340b08","infoHashBuffer":{"type":"Buffer","data":[67,113,242,46,10,247,205,226,67,89,117,187,189,82,25,182,180,52,11,8]},"announce":[],"urlList":[]}}