{"title":"NoBoring - Anita Baby ** NEW 24 January 2016 **","uid":13296335,"size":424838584,"categoryP":"porn","categoryS":"movie_clips","magnet":"?xt=urn:btih:4a3ad8a7e54758cc6b85669b2443698a039d0fe7&amp;dn=NoBoring+-+Anita+Baby+%2A%2A+NEW+24+January+2016+%2A%2A&amp;tr=udp%3A%2F%2Ftracker.leechers-paradise.org%3A6969&amp;tr=udp%3A%2F%2Fzer0day.ch%3A1337&amp;tr=udp%3A%2F%2Fopen.demonii.com%3A1337&amp;tr=udp%3A%2F%2Ftracker.coppersurfer.tk%3A6969&amp;tr=udp%3A%2F%2Fexodus.desync.com%3A6969","seeders":1,"leechers":0,"uploader":"SudoSu","files":1,"time":1453639478,"description":"\nhttp://youpornbook.com\r\n\r\n―――――――――――――――――――――――――\r\n ... : Screenshots : ... \r\n―――――――――――――――――――――――――   \nhttp://imgpremium.com/image/gI4 \nhttp://imgpremium.com/image/gI8\r\n\r\nAnal, Sex Toys, All Sex\r\n\r\nThe sultry, sexy blonde in whore makeup stretches her lips around his big cock to give a blowjob and sits on him in ripped pantyhose for a hot ride with her cunt. She wants that ass fucking action and he makes sure to ream out her asshole with his thickness, pulling out to have her suck it clean and banging her pussy with a big dirty cock too.\r\n\r\nMore exclusive porn at:  https://thepiratebay.se/user/SudoSu/","torrent":{"xt":"urn:btih:4a3ad8a7e54758cc6b85669b2443698a039d0fe7","amp;dn":"NoBoring+-+Anita+Baby+%2A%2A+NEW+24+January+2016+%2A%2A","amp;tr":["udp%3A%2F%2Ftracker.leechers-paradise.org%3A6969","udp%3A%2F%2Fzer0day.ch%3A1337","udp%3A%2F%2Fopen.demonii.com%3A1337","udp%3A%2F%2Ftracker.coppersurfer.tk%3A6969","udp%3A%2F%2Fexodus.desync.com%3A6969"],"infoHash":"4a3ad8a7e54758cc6b85669b2443698a039d0fe7","infoHashBuffer":{"type":"Buffer","data":[74,58,216,167,229,71,88,204,107,133,102,155,36,67,105,138,3,157,15,231]},"announce":[],"urlList":[]}}