{"title":"The Jack Benny Program - s03e07 - Fred Allen Show (1953)","uid":4418257,"size":182777856,"categoryP":"video","categoryS":"tv_shows","magnet":"?xt=urn:btih:4ac72243f85fc7b1022b002c0d4f32e3c1f6e193&amp;dn=The+Jack+Benny+Program+-+s03e07+-+Fred+Allen+Show+%281953%29&amp;tr=udp%3A%2F%2Ftracker.openbittorrent.com%3A80&amp;tr=udp%3A%2F%2Fopen.demonii.com%3A1337&amp;tr=udp%3A%2F%2Ftracker.coppersurfer.tk%3A6969&amp;tr=udp%3A%2F%2Fexodus.desync.com%3A6969","seeders":1,"leechers":0,"uploader":"sparkster22222","files":1,"time":1222637912,"description":"While rehearsing for his show, the producers give him a two hour break and Jack decides to visit his sponsor to renew his option. While waiting in the lobby, Fred Allen is inside talking with Mr. Lewis, President and sponsor. Allen is trying to convince Mr. Lewis not to renew Jack's option and hire him instead.\n\nVideo: XVID 416x304 29.97fps 836Kbps\nAudio: MPEG Audio Layer 3 48000Hz stereo 124Kbps\nRunning time: 0:24:59","torrent":{"xt":"urn:btih:4ac72243f85fc7b1022b002c0d4f32e3c1f6e193","amp;dn":"The+Jack+Benny+Program+-+s03e07+-+Fred+Allen+Show+%281953%29","amp;tr":["udp%3A%2F%2Ftracker.openbittorrent.com%3A80","udp%3A%2F%2Fopen.demonii.com%3A1337","udp%3A%2F%2Ftracker.coppersurfer.tk%3A6969","udp%3A%2F%2Fexodus.desync.com%3A6969"],"infoHash":"4ac72243f85fc7b1022b002c0d4f32e3c1f6e193","infoHashBuffer":{"type":"Buffer","data":[74,199,34,67,248,95,199,177,2,43,0,44,13,79,50,227,193,246,225,147]},"announce":[],"urlList":[]}}