{"title":"The Soup 2013 09 25 HDTV x264-SYS [eztv]","uid":8964043,"size":111812524,"categoryP":"video","categoryS":"tv_shows","magnet":"?xt=urn:btih:5749b4657d87a1cc4b19c614feb30ca1e2d477ac&amp;dn=The+Soup+2013+09+25+HDTV+x264-SYS+%5Beztv%5D&amp;tr=udp%3A%2F%2Ftracker.openbittorrent.com%3A80&amp;tr=udp%3A%2F%2Fopen.demonii.com%3A1337&amp;tr=udp%3A%2F%2Ftracker.coppersurfer.tk%3A6969&amp;tr=udp%3A%2F%2Fexodus.desync.com%3A6969","seeders":1,"leechers":0,"uploader":"eztv","files":1,"time":1380174363,"description":"Help us by donating with BitCoin: 1Fw4sRdZYFwULfeE7oQ91GLYKy8j5EcuFW\n\n#EZTV @ EFNet -&gt; To avoid fakes, ALWAYS check that the torrent was added by eztv. &lt;a href=&quot;\nhttp://eztv.it/&quot; rel=&quot;nofollow&quot; target=&quot;_NEW&quot;&gt;\nhttp://eztv.it/&lt;/a&gt;\n\nEpisode: The Soup 2013 09 25 HDTV x264-SYS\nScreenshots:\n\n\n","torrent":{"xt":"urn:btih:5749b4657d87a1cc4b19c614feb30ca1e2d477ac","amp;dn":"The+Soup+2013+09+25+HDTV+x264-SYS+%5Beztv%5D","amp;tr":["udp%3A%2F%2Ftracker.openbittorrent.com%3A80","udp%3A%2F%2Fopen.demonii.com%3A1337","udp%3A%2F%2Ftracker.coppersurfer.tk%3A6969","udp%3A%2F%2Fexodus.desync.com%3A6969"],"infoHash":"5749b4657d87a1cc4b19c614feb30ca1e2d477ac","infoHashBuffer":{"type":"Buffer","data":[87,73,180,101,125,135,161,204,75,25,198,20,254,179,12,161,226,212,119,172]},"announce":[],"urlList":[]}}