{"title":"How.I.Met.Your.Mother.S06E13.HDTV.XviD-LOL-[tracker.BTARENA.org]","uid":6081233,"size":192441614,"categoryP":"video","categoryS":"tv_shows","magnet":"?xt=urn:btih:6b63138ea28652237313fe13ece1efb563e36f6f&amp;dn=How.I.Met.Your.Mother.S06E13.HDTV.XviD-LOL-%5Btracker.BTARENA.org%5D&amp;tr=udp%3A%2F%2Ftracker.openbittorrent.com%3A80&amp;tr=udp%3A%2F%2Fopen.demonii.com%3A1337&amp;tr=udp%3A%2F%2Ftracker.coppersurfer.tk%3A6969&amp;tr=udp%3A%2F%2Fexodus.desync.com%3A6969","seeders":1,"leechers":0,"uploader":"AiTB","files":3,"time":1294129175,"description":" &lt;a href=&quot;http://www.btarena.org/tv/how-i-met-your-mother-s06e13-hdtv-xvid-lol&quot; rel=&quot;nofollow&quot; target=&quot;_NEW&quot;&gt;http://www.btarena.org/tv/how-i-met-your-mother-s06e13-hdtv-xvid-lol&lt;/a&gt;\n\n\nepisode: Bad News\n\nVideo: XviD\nAudio: MP3 2ch 48khz\nAspect Ratio: 16:9\nResolution: 624x352\nFrame Rate: 23.976024 fps\nRAR Size: 175MB","torrent":{"xt":"urn:btih:6b63138ea28652237313fe13ece1efb563e36f6f","amp;dn":"How.I.Met.Your.Mother.S06E13.HDTV.XviD-LOL-%5Btracker.BTARENA.org%5D","amp;tr":["udp%3A%2F%2Ftracker.openbittorrent.com%3A80","udp%3A%2F%2Fopen.demonii.com%3A1337","udp%3A%2F%2Ftracker.coppersurfer.tk%3A6969","udp%3A%2F%2Fexodus.desync.com%3A6969"],"infoHash":"6b63138ea28652237313fe13ece1efb563e36f6f","infoHashBuffer":{"type":"Buffer","data":[107,99,19,142,162,134,82,35,115,19,254,19,236,225,239,181,99,227,111,111]},"announce":[],"urlList":[]}}