{"title":"The.Daily.Show.2015.06.30.Jon.Hamm.HDTV.x264-CROOKS.[VTV].mp4","uid":12081615,"size":158105378,"categoryP":"video","categoryS":"tv_shows","magnet":"?xt=urn:btih:6dd67a6416df6db6f23c4084b6ae9221e44052d7&amp;dn=The.Daily.Show.2015.06.30.Jon.Hamm.HDTV.x264-CROOKS.%5BVTV%5D.mp4&amp;tr=udp%3A%2F%2Ftracker.openbittorrent.com%3A80&amp;tr=udp%3A%2F%2Fopen.demonii.com%3A1337&amp;tr=udp%3A%2F%2Ftracker.coppersurfer.tk%3A6969&amp;tr=udp%3A%2F%2Fexodus.desync.com%3A6969","seeders":1,"leechers":0,"uploader":"VTV","files":1,"time":1435785164,"description":"The Daily Show 2015.06.30 (HDTV-x264-CROOKS)[VTV]","torrent":{"xt":"urn:btih:6dd67a6416df6db6f23c4084b6ae9221e44052d7","amp;dn":"The.Daily.Show.2015.06.30.Jon.Hamm.HDTV.x264-CROOKS.%5BVTV%5D.mp4","amp;tr":["udp%3A%2F%2Ftracker.openbittorrent.com%3A80","udp%3A%2F%2Fopen.demonii.com%3A1337","udp%3A%2F%2Ftracker.coppersurfer.tk%3A6969","udp%3A%2F%2Fexodus.desync.com%3A6969"],"infoHash":"6dd67a6416df6db6f23c4084b6ae9221e44052d7","infoHashBuffer":{"type":"Buffer","data":[109,214,122,100,22,223,109,182,242,60,64,132,182,174,146,33,228,64,82,215]},"announce":[],"urlList":[]}}