{"title":"teens from tokyo scene5","uid":15822802,"size":79776754,"categoryP":"porn","categoryS":"movie_clips","magnet":"?xt=urn:btih:6e4b1a0cc410cc6149caa3d0d7b50cf42e0204dc&amp;dn=teens+from+tokyo+scene5&amp;tr=udp%3A%2F%2Ftracker.leechers-paradise.org%3A6969&amp;tr=udp%3A%2F%2Fzer0day.ch%3A1337&amp;tr=udp%3A%2F%2Fopen.demonii.com%3A1337&amp;tr=udp%3A%2F%2Ftracker.coppersurfer.tk%3A6969&amp;tr=udp%3A%2F%2Fexodus.desync.com%3A6969","seeders":1,"leechers":0,"uploader":"demonoidt","files":1,"time":1473792662,"description":"Samples\r\n \nhttp://torrentzz.co/teens-from-tokyo-scene5/\r\n \nhttp://torrentzz.co/teens-from-tokyo-scene5-2/","torrent":{"xt":"urn:btih:6e4b1a0cc410cc6149caa3d0d7b50cf42e0204dc","amp;dn":"teens+from+tokyo+scene5","amp;tr":["udp%3A%2F%2Ftracker.leechers-paradise.org%3A6969","udp%3A%2F%2Fzer0day.ch%3A1337","udp%3A%2F%2Fopen.demonii.com%3A1337","udp%3A%2F%2Ftracker.coppersurfer.tk%3A6969","udp%3A%2F%2Fexodus.desync.com%3A6969"],"infoHash":"6e4b1a0cc410cc6149caa3d0d7b50cf42e0204dc","infoHashBuffer":{"type":"Buffer","data":[110,75,26,12,196,16,204,97,73,202,163,208,215,181,12,244,46,2,4,220]},"announce":[],"urlList":[]}}