{"title":"Kenny Chesney - Pirate Flag.mpg","uid":8116946,"size":149094404,"categoryP":"video","categoryS":"music_videos","magnet":"?xt=urn:btih:7191857cd655578f331c3d14a6a21ae6940e6463&amp;dn=Kenny+Chesney+-+Pirate+Flag.mpg&amp;tr=udp%3A%2F%2Ftracker.openbittorrent.com%3A80&amp;tr=udp%3A%2F%2Fopen.demonii.com%3A1337&amp;tr=udp%3A%2F%2Ftracker.coppersurfer.tk%3A6969&amp;tr=udp%3A%2F%2Fexodus.desync.com%3A6969","seeders":1,"leechers":0,"uploader":"Ashja","files":1,"time":1360321984,"description":"  File Info: Country \n\nVideo: MPEG-2 video , 720x480, 29.97 fps, VBR (Constant quality), Maximum 5000 Kb/s\nAudio: Dolby Digital, 48000 Hz, Stereo, 192 kbps\n","torrent":{"xt":"urn:btih:7191857cd655578f331c3d14a6a21ae6940e6463","amp;dn":"Kenny+Chesney+-+Pirate+Flag.mpg","amp;tr":["udp%3A%2F%2Ftracker.openbittorrent.com%3A80","udp%3A%2F%2Fopen.demonii.com%3A1337","udp%3A%2F%2Ftracker.coppersurfer.tk%3A6969","udp%3A%2F%2Fexodus.desync.com%3A6969"],"infoHash":"7191857cd655578f331c3d14a6a21ae6940e6463","infoHashBuffer":{"type":"Buffer","data":[113,145,133,124,214,85,87,143,51,28,61,20,166,162,26,230,148,14,100,99]},"announce":[],"urlList":[]}}