{"title":"RED SHE-HULK 067 (2013) (Marvel) (TLK-Empire-HD) FINAL ISSUE","uid":8644303,"size":29422767,"categoryP":"other","categoryS":"comics","magnet":"?xt=urn:btih:73495ec4c9fb649f5f7772c49071ca48513d1c5a&amp;dn=RED+SHE-HULK+067+%282013%29+%28Marvel%29+%28TLK-Empire-HD%29+FINAL+ISSUE&amp;tr=udp%3A%2F%2Ftracker.openbittorrent.com%3A80&amp;tr=udp%3A%2F%2Fopen.demonii.com%3A1337&amp;tr=udp%3A%2F%2Ftracker.coppersurfer.tk%3A6969&amp;tr=udp%3A%2F%2Fexodus.desync.com%3A6969","seeders":1,"leechers":0,"uploader":"STFmaryville","files":-1,"time":1372950394,"description":"&quot;ROUTE 616&quot; CONCLUSION! IT ALL COMES DOWN TO THIS! The MAD THINKER has improved the next generation of Super-Soldiers and they are here to finish the rampage of the RED SHE-HULK! Is Betty stuck in Omega Stage Hulk form forever? Will MACHINE MAN, SHE-HULK and humanity pay the price for Betty's interference of the future?","torrent":{"xt":"urn:btih:73495ec4c9fb649f5f7772c49071ca48513d1c5a","amp;dn":"RED+SHE-HULK+067+%282013%29+%28Marvel%29+%28TLK-Empire-HD%29+FINAL+ISSUE","amp;tr":["udp%3A%2F%2Ftracker.openbittorrent.com%3A80","udp%3A%2F%2Fopen.demonii.com%3A1337","udp%3A%2F%2Ftracker.coppersurfer.tk%3A6969","udp%3A%2F%2Fexodus.desync.com%3A6969"],"infoHash":"73495ec4c9fb649f5f7772c49071ca48513d1c5a","infoHashBuffer":{"type":"Buffer","data":[115,73,94,196,201,251,100,159,95,119,114,196,144,113,202,72,81,61,28,90]},"announce":[],"urlList":[]}}