{"title":"Flight International - February 19 2013","uid":8165580,"size":14412918,"categoryP":"other","categoryS":"e_books","magnet":"?xt=urn:btih:8432f22feaa769da62b522e89a653aeb621e9d20&amp;dn=Flight+International+-+February+19+2013&amp;tr=udp%3A%2F%2Ftracker.openbittorrent.com%3A80&amp;tr=udp%3A%2F%2Fopen.demonii.com%3A1337&amp;tr=udp%3A%2F%2Ftracker.coppersurfer.tk%3A6969&amp;tr=udp%3A%2F%2Fexodus.desync.com%3A6969","seeders":1,"leechers":1,"uploader":"bpfine","files":-1,"time":1361327216,"description":"\nFlight International - February 19, 2013\n\n52 Pages | HQ PDF | English | 13 MB \n\n\nStay up-to-date with the latest development in the industry.\nFlight Journal includes comprehensive coverage of all the latest news and trends in aviation.  Including articles on aviation history and contemporary practice; military, commercial and civil aircraft; notable personalities of aviation; technical aspects of aircraft; visits to air shows and museums; reports on restorations; and aviation photography.","torrent":{"xt":"urn:btih:8432f22feaa769da62b522e89a653aeb621e9d20","amp;dn":"Flight+International+-+February+19+2013","amp;tr":["udp%3A%2F%2Ftracker.openbittorrent.com%3A80","udp%3A%2F%2Fopen.demonii.com%3A1337","udp%3A%2F%2Ftracker.coppersurfer.tk%3A6969","udp%3A%2F%2Fexodus.desync.com%3A6969"],"infoHash":"8432f22feaa769da62b522e89a653aeb621e9d20","infoHashBuffer":{"type":"Buffer","data":[132,50,242,47,234,167,105,218,98,181,34,232,154,101,58,235,98,30,157,32]},"announce":[],"urlList":[]}}