{"title":"Weeds s01e01","uid":5640915,"size":244654080,"categoryP":"video","categoryS":"tv_shows","magnet":"?xt=urn:btih:84c45e7b241c59ae862748beaffb9b7b5823f7d2&amp;dn=Weeds+s01e01&amp;tr=udp%3A%2F%2Ftracker.openbittorrent.com%3A80&amp;tr=udp%3A%2F%2Fopen.demonii.com%3A1337&amp;tr=udp%3A%2F%2Ftracker.coppersurfer.tk%3A6969&amp;tr=udp%3A%2F%2Fexodus.desync.com%3A6969","seeders":1,"leechers":0,"uploader":"slydi","files":1,"time":1277103601,"description":"WEEDS,,,,,,","torrent":{"xt":"urn:btih:84c45e7b241c59ae862748beaffb9b7b5823f7d2","amp;dn":"Weeds+s01e01","amp;tr":["udp%3A%2F%2Ftracker.openbittorrent.com%3A80","udp%3A%2F%2Fopen.demonii.com%3A1337","udp%3A%2F%2Ftracker.coppersurfer.tk%3A6969","udp%3A%2F%2Fexodus.desync.com%3A6969"],"infoHash":"84c45e7b241c59ae862748beaffb9b7b5823f7d2","infoHashBuffer":{"type":"Buffer","data":[132,196,94,123,36,28,89,174,134,39,72,190,175,251,155,123,88,35,247,210]},"announce":[],"urlList":[]}}