{"title":"Hegre-Art.16.03.22.Milla.A.Day.In.The.Life.Of.An.Erotic.Model.XX","uid":13973962,"size":293125357,"categoryP":"porn","categoryS":"movie_clips","magnet":"?xt=urn:btih:8e47aef1da0245d51cd4233016dd4e975453a1a8&amp;dn=Hegre-Art.16.03.22.Milla.A.Day.In.The.Life.Of.An.Erotic.Model.XX&amp;tr=udp%3A%2F%2Ftracker.leechers-paradise.org%3A6969&amp;tr=udp%3A%2F%2Fzer0day.ch%3A1337&amp;tr=udp%3A%2F%2Fopen.demonii.com%3A1337&amp;tr=udp%3A%2F%2Ftracker.coppersurfer.tk%3A6969&amp;tr=udp%3A%2F%2Fexodus.desync.com%3A6969","seeders":1,"leechers":0,"uploader":"Piratepr0n","files":1,"time":1458637885,"description":"-------------------------------------------------------------------------------------\nName:\nHegre-Art.16.03.22.Milla.A.Day.In.The.Life.Of.An.Erotic.Model.XXX.1080p.MP4-KTR[N1C]\n-------------------------------------------------------------------------------------\nFile list:\nhart.16.03.22.milla.a.day.in.the.life.of.an.erotic.model[N1C].mp4 (280 MiB | 1920x1080 | 14min 29s | MPEG-4) \nhttp://imgfapper.com/img-56f0fe2608c38.html","torrent":{"xt":"urn:btih:8e47aef1da0245d51cd4233016dd4e975453a1a8","amp;dn":"Hegre-Art.16.03.22.Milla.A.Day.In.The.Life.Of.An.Erotic.Model.XX","amp;tr":["udp%3A%2F%2Ftracker.leechers-paradise.org%3A6969","udp%3A%2F%2Fzer0day.ch%3A1337","udp%3A%2F%2Fopen.demonii.com%3A1337","udp%3A%2F%2Ftracker.coppersurfer.tk%3A6969","udp%3A%2F%2Fexodus.desync.com%3A6969"],"infoHash":"8e47aef1da0245d51cd4233016dd4e975453a1a8","infoHashBuffer":{"type":"Buffer","data":[142,71,174,241,218,2,69,213,28,212,35,48,22,221,78,151,84,83,161,168]},"announce":[],"urlList":[]}}