{"title":"Faith No More - Album Of The Year (1997/2002) (Lossless)","uid":5589970,"size":1479560738,"categoryP":"audio","categoryS":"music","magnet":"?xt=urn:btih:91a6dbe9e4b1676642fa41823a9d03dd4579084a&amp;dn=Faith+No+More+-+Album+Of+The+Year+%281997%2F2002%29+%28Lossless%29&amp;tr=udp%3A%2F%2Ftracker.openbittorrent.com%3A80&amp;tr=udp%3A%2F%2Fopen.demonii.com%3A1337&amp;tr=udp%3A%2F%2Ftracker.coppersurfer.tk%3A6969&amp;tr=udp%3A%2F%2Fexodus.desync.com%3A6969","seeders":1,"leechers":0,"uploader":"Dominus.ORTUS","files":-1,"time":1274830515,"description":"Faith No More - &quot;Album Of The Year&quot; (1997/2002)\n\nCountry:\tUK\nCodec: \t\tWMA\nQuality: \tLossless\nChannels: \t2\nSR/SS:\t\t44.1 kHz/16 bit\n\nOriginal Edition\nGenre: \t\tAlternative Rock\nYear:\t\t1997\nSource: \tCD\nTrack List:\n1.\tCollision\n2.\tStripsearch\n3.\tLast Cup Of Sorrow\n4.\tNaked In Front Of The Computer\n5.\tHelpless\n6.\tMouth To Mouth\n7.\tAshes To Ashes\n8.\tShe Loves Me Not\n9.\tGot That Feeling\n10.\tPaths Of Glory\n11.\tHome Sick Home\n12.\tPristina\n\nLimited Competition Edition\nGenre: \t\tAlternative Rock, Industrial Metal, Breakbeat, Dub, House\nYear:\t\t1997/2002\nSource: \tCD\nTrack List:\n1.\tCollision\n2.\tStripsearch\n3.\tLast Cup Of Sorrow\n4.\tNaked In Front Of The Computer\n5.\tHelpless\n6.\tMouth To Mouth\n7.\tAshes To Ashes\n8.\tShe Loves Me Not\n9.\tGot That Feeling\n10.\tPaths Of Glory\n11.\tHome Sick Home\n12.\tPristina\n13.\tThe Big Kahuna\n14.\tLight Up And Let Go\n15.\tLast Cup Of Sorrow (Rammstein Mix)\n16.\tAshes To Ashes (Hardknox Alternative Mix)\n17.\tShe Loves Me Not (Spinna Crazy Dub Mix)\n18.\tLast Cup Of Sorrow (Sharam Versus FNM Club Mix)\n\nLimited Edition\nGenre: \t\tAlternative Rock, Breakbeat, Drum and Base\nYear:\t\t1997/2002\nSource: \t2 CD\nTrack List:\n1.\tCollision\n2.\tStripsearch\n3.\tLast Cup Of Sorrow\n4.\tNaked In Front Of The Computer\n5.\tHelpless\n6.\tMouth To Mouth\n7.\tAshes To Ashes\n8.\tShe Loves Me Not\n9.\tGot That Feeling\n10.\tPaths Of Glory\n11.\tHome Sick Home\n12.\tPristina\n13.\tLast Cup Of Sorrow (Bigfoot and Wildboy Mix)\n14.\tLast Cup Of Sorrow (Bonehead Mix)\n15.\tAshes To Ashes (Hardknox Horned Hand Mix)\n16.\tAshes To Ashes (Automatic 5 Dub)\n17.\tShe Loves Me Not (Spinna Main Mix)\n18.\tAshes To Ashes (Dillinja Mix)","torrent":{"xt":"urn:btih:91a6dbe9e4b1676642fa41823a9d03dd4579084a","amp;dn":"Faith+No+More+-+Album+Of+The+Year+%281997%2F2002%29+%28Lossless%29","amp;tr":["udp%3A%2F%2Ftracker.openbittorrent.com%3A80","udp%3A%2F%2Fopen.demonii.com%3A1337","udp%3A%2F%2Ftracker.coppersurfer.tk%3A6969","udp%3A%2F%2Fexodus.desync.com%3A6969"],"infoHash":"91a6dbe9e4b1676642fa41823a9d03dd4579084a","infoHashBuffer":{"type":"Buffer","data":[145,166,219,233,228,177,103,102,66,250,65,130,58,157,3,221,69,121,8,74]},"announce":[],"urlList":[]}}