{"title":"Counter Strike - Global Offensive (Warzone) [+Autoupdate]","uid":12143562,"size":4192711255,"categoryP":"games","categoryS":"pc","magnet":"?xt=urn:btih:aeda06a55b45837503efa931f4b752fe5104791d&amp;dn=Counter+Strike+-+Global+Offensive+%28Warzone%29+%5B%2BAutoupdate%5D&amp;tr=udp%3A%2F%2Ftracker.openbittorrent.com%3A80&amp;tr=udp%3A%2F%2Fopen.demonii.com%3A1337&amp;tr=udp%3A%2F%2Ftracker.coppersurfer.tk%3A6969&amp;tr=udp%3A%2F%2Fexodus.desync.com%3A6969","seeders":1,"leechers":0,"uploader":"bubobih","files":1,"time":1437410097,"description":"Description\nCounter-Strike: Global Offensive - WaRzOnE LATEST REPACK\nSite: www.cswarzone.com\nForum: www.csgowarzone.com\n\nFEATURES\n- 100% clean rip from Steam game content\n- 3.5GB highly compressed installer size\n- Include build-in auto updater\n- Working game inventory and items\n- Working server browser with Internet, Favourite and LAN tabs\n- Working offline mode with bots\n- Playable on Internet and LAN\n- Compatible with Windows 8/7/Vista\n\nIMPORTANT NOTE\nSome Antivirus software might detect false positive virus.\nUse some good Antivirus software like Avast or ESET NOD32.\nIf launcher hangs run with admin rights.\nInstall All in One Runtimes which update DirectX and install .NET Framework 4.\nOn first launch click update button to download game files.\n\nPC REQUIREMENTS\n- OS: WindowsÂ® 8/7/Vista\n- Processor: IntelÂ® Coreâ„¢ 2 Duo E6600 or AMD Phenomâ„¢ X3 8750 processor or better\n- Memory: 1GB XP / 2GB Vista\n- Hard Disk Space: At least 7.6GB of Space\n- Video Card: Video card must be 256 MB or more and should be a DirectX 9-C with Pixel Shader 3.0\n\nCREDITS\nCounter-Strike: Global Offensive - Valve\nDevelopers - bir3yk, MAMACâ„¢\nInstaller - MAMACâ„¢\n\nÂ© 2011-2015 CSwarzone\n\nPlease, SEED!","torrent":{"xt":"urn:btih:aeda06a55b45837503efa931f4b752fe5104791d","amp;dn":"Counter+Strike+-+Global+Offensive+%28Warzone%29+%5B%2BAutoupdate%5D","amp;tr":["udp%3A%2F%2Ftracker.openbittorrent.com%3A80","udp%3A%2F%2Fopen.demonii.com%3A1337","udp%3A%2F%2Ftracker.coppersurfer.tk%3A6969","udp%3A%2F%2Fexodus.desync.com%3A6969"],"infoHash":"aeda06a55b45837503efa931f4b752fe5104791d","infoHashBuffer":{"type":"Buffer","data":[174,218,6,165,91,69,131,117,3,239,169,49,244,183,82,254,81,4,121,29]},"announce":[],"urlList":[]}}