{"title":"Sport.Science.S02E09.720p.HDTV.x264-CBFM","uid":11916491,"size":1230509477,"categoryP":"video","categoryS":"hd___tv_shows","magnet":"?xt=urn:btih:b6beeb9e8fa89d2e9219b2ed25479a0fad2d8812&amp;dn=Sport.Science.S02E09.720p.HDTV.x264-CBFM&amp;tr=udp%3A%2F%2Ftracker.openbittorrent.com%3A80&amp;tr=udp%3A%2F%2Fopen.demonii.com%3A1337&amp;tr=udp%3A%2F%2Ftracker.coppersurfer.tk%3A6969&amp;tr=udp%3A%2F%2Fexodus.desync.com%3A6969","seeders":1,"leechers":0,"uploader":"sceneline","files":5,"time":1431549668,"description":"Hey visit my site\n\nFollow us on Facebook  /Speeddotcd\n\nFor the sake of sharing, Please seed as long as you can\n\nEnjoy HD releases \n\n ............ NFO .............\n-\t\nFor more info about this show check NFO file","torrent":{"xt":"urn:btih:b6beeb9e8fa89d2e9219b2ed25479a0fad2d8812","amp;dn":"Sport.Science.S02E09.720p.HDTV.x264-CBFM","amp;tr":["udp%3A%2F%2Ftracker.openbittorrent.com%3A80","udp%3A%2F%2Fopen.demonii.com%3A1337","udp%3A%2F%2Ftracker.coppersurfer.tk%3A6969","udp%3A%2F%2Fexodus.desync.com%3A6969"],"infoHash":"b6beeb9e8fa89d2e9219b2ed25479a0fad2d8812","infoHashBuffer":{"type":"Buffer","data":[182,190,235,158,143,168,157,46,146,25,178,237,37,71,154,15,173,45,136,18]},"announce":[],"urlList":[]}}