{"title":"Backwoods Institute of Psychological Technology e Book Archive.z","uid":4015052,"size":1568974334,"categoryP":"other","categoryS":"e_books","magnet":"?xt=urn:btih:c667be50b49a48615a90018724aa8c9af9c1776e&amp;dn=Backwoods+Institute+of+Psychological+Technology+e+Book+Archive.z&amp;tr=udp%3A%2F%2Ftracker.openbittorrent.com%3A80&amp;tr=udp%3A%2F%2Fopen.demonii.com%3A1337&amp;tr=udp%3A%2F%2Ftracker.coppersurfer.tk%3A6969&amp;tr=udp%3A%2F%2Fexodus.desync.com%3A6969","seeders":1,"leechers":0,"uploader":"Glandmaster","files":1,"time":1202314849,"description":"Apparently this page is closing:\n &lt;a href=&quot;\nhttp://www.docquan.com/lib_dead.html&quot; rel=&quot;nofollow&quot; target=&quot;_NEW&quot;&gt;\nhttp://www.docquan.com/lib_dead.html&lt;/a&gt;\n\nSo heres the files in a zip ;)\n\nNLP, Hypnosis, Persuasion \nOccult and Esoteric \nDrugs, Psychedelics \nMilitary, Gov Documents, Warfare \nUFOlogy and the Paranormal\nPolitical Science, History, Social Control\nDIY, How-To, Home Projects \nScience - Physics, Biology, Astronomy, etc","torrent":{"xt":"urn:btih:c667be50b49a48615a90018724aa8c9af9c1776e","amp;dn":"Backwoods+Institute+of+Psychological+Technology+e+Book+Archive.z","amp;tr":["udp%3A%2F%2Ftracker.openbittorrent.com%3A80","udp%3A%2F%2Fopen.demonii.com%3A1337","udp%3A%2F%2Ftracker.coppersurfer.tk%3A6969","udp%3A%2F%2Fexodus.desync.com%3A6969"],"infoHash":"c667be50b49a48615a90018724aa8c9af9c1776e","infoHashBuffer":{"type":"Buffer","data":[198,103,190,80,180,154,72,97,90,144,1,135,36,170,140,154,249,193,119,110]},"announce":[],"urlList":[]}}