{"title":"NRJ Les Hits Du Moment December  2015","uid":13129170,"size":880840501,"categoryP":"audio","categoryS":"music","magnet":"?xt=urn:btih:ca3c810b293f51382b4bb58cbe9b2ea1f38866bb&amp;dn=NRJ+Les+Hits+Du+Moment+December++2015&amp;tr=udp%3A%2F%2Ftracker.leechers-paradise.org%3A6969&amp;tr=udp%3A%2F%2Fzer0day.ch%3A1337&amp;tr=udp%3A%2F%2Fopen.demonii.com%3A1337&amp;tr=udp%3A%2F%2Ftracker.coppersurfer.tk%3A6969&amp;tr=udp%3A%2F%2Fexodus.desync.com%3A6969","seeders":1,"leechers":0,"uploader":"RoffeTheCoolMan","files":100,"time":1451820715,"description":"Playlist NRJ Les Hits Du Moment December 2015\r\n\r\n\r\n01. Matt Simons - Catch &amp; Release\r\n02. Jay Z &amp; Matoma - Roc Boys\r\n03. Josef Salvat - Le Paradis Nous Trouvera (Paradise)\r\n04. Coldplay - Adventure Of A Lifetime\r\n05. Sia - Cheap Thrills\r\n06. MaМtre Gims - Tu Vas Me Manquer\r\n07. David Guetta Feat. Sia &amp; Fetty Wap - Bang My Head\r\n08. Sihar - Spell\r\n09. Soprano - Barman\r\n10. Yall Feat. Gabriela Richardson - Hundred Miles\r\n11. MO - Kamikaze\r\n12. Sch - Fusil\r\n13. Pia Mia - Touch\r\n14. Justin Bieber - Sorry\r\n15. Drake - Hotline Bling\r\n16. Seth Gueko Feat. Oxmo Puccino &amp; Nekfeu - Titi Parisien\r\n17. DJ Snake Feat. Bipolar Sunshine - Middle\r\n18. Feder Feat. Emmi - Blind\r\n19. Adele - Hello\r\n20. MylКne Farmer - City Of Love\r\n21. The Avener &amp; Kim Churchill - You're My Window To The Sky\r\n22. Oscar And The Wolf Feat. Tsar B - Back to Black\r\n23. Louane - Maman\r\n24. H Magnum - Braquer Nos RИves\r\n25. Willy William - Ego\r\n26. Madcon Feat. Ray Dalton - Don't Worry [Radio Edit]\r\n27. Maroon 5 - Feelings\r\n28. Kids United - On Ecrit Sur Les Murs\r\n29. Dzeko &amp; Torres Feat. Delaney Jane - L'amour Toujours\r\n30. Sandra Lyng - Play My Drum\r\n31. Christine and The Queens - Paradis Perdus\r\n32. Gradur - Rosa\r\n33. Shawn Mendes - Stitches\r\n34. MaМtre Gims &amp; Niska - SapВs Comme Jamais\r\n35. Sigala - Sweet Lovin\r\n36. Major Lazer &amp; Moti Feat TY Dolla $ign, Wizkid, &amp; Kranium - Boom\r\n37. Chris Brown- Back To Sleep\r\n38. Booba - 92i Veyron\r\n39. Tenny - Caramel Beurre Sale\r\n40. Ridsa - LЕ C'est Die\r\n41. Calvin Harris &amp; Disciples - How Deep Is Your Love\r\n42. Casseurs Flowters - A l'heure OЧ Je Me Couche\r\n43. Robin Schulz &amp; Judge - Show Me Love\r\n44. Ty Dolla $ign Feat. E-40 - Saved\r\n45. Kiiara - Gold\r\n46. James Bay - If You Ever Want To Be In Love\r\n47. Lacrim - J'ai Mal\r\n48. Alessia Cara - Here\r\n49. Empire Cast Feat. Jussie Smollett - Good Enough\r\n50. Kygo Feat. Maty Noyes - Stay\r\n51. Synapson Feat. Anna Kova - All In You\r\n52. Brice Conrad - A Tort Ou Е Raison (Remix)\r\n53. Sia - Bird Set Free\r\n54. Robin Schulz Feat. Francesco Yates - Sugar\r\n55. Jul - Wesh Alors\r\n56. Lefa - Quelques Minutes\r\n57. La Fouine Feat. Lartiste - Insta\r\n58. Selena Gomez - Me &amp; The Rhythm\r\n59. Navii - J'Вcoute Du Miles Davis\r\n60. Justin Bieber - What Do You Mean\r\n61. Andrea &amp; Otilia Feat. Shaggy &amp; Costi - Passion\r\n62. Franko - Coller La Petite\r\n63. Baby K Feat. Giusy Ferreri - Roma\r\n64. Dimitri Vegas &amp; Like Mike Feat. Ne-Yo - Higher Place\r\n65. Keen'V - Un Monde Meilleur\r\n66. TiЙsto &amp; The Chainsmokers - Split (Only U) [Radio Edit]\r\n67. Blue Velvet - Blue\r\n68. WatermДt &amp; Tai - Frequency [Radio Edit]\r\n69. Izzy Bizu - White Tiger\r\n70. Eva Simons Feat. Sidney Samson - Bludfire\r\n71. R. City Feat. Chloe Angelides - Make Up\r\n72. FrВro Delavega - Autour De Moi\r\n73. Avicii Feat. Zac Brown - Broken Arrows\r\n74. Geronimo - PossВdВs [Radio Edit]\r\n75. Ariana Grande - Focus\r\n76. Vitaa - T'es OЧ\r\n77. Wstrn - In2\r\n78. Kendji Girac - Les Yeux De La Mama\r\n79. Topic Feat. Lili Pistorius - Fly Away\r\n80. Julian Perretta - Miracle\r\n81. Anggun &amp; Florent Pagny - Nos Vies ParallКles\r\n82. Les 3 Mousquetaires - Un Jour (Damien Sargue)\r\n83. LoЛc Nottet - Rhythm Inside\r\n84. Madilyn Bailey - Believe\r\n85. Soom T - Broken Robots\r\n86. The Weeknd Feat. Eminem - The Hills\r\n87. DNCE - Cake By The Ocean\r\n88. L.E.J - Hip Hop Mash Up\r\n89. Breakbot - Get Lost\r\n90. Tropkillaz - Baby Baby\r\n91. Major Lazer Feat. Nyla &amp; Fuse ODG - Light It Up [Remix]\r\n92. Shaun Frank Feat. Delaney Jane - Heaven [Radio Edit]\r\n93. Years &amp; Years - Desire (Gryffin)\r\n94. Sander Van Doorn &amp; Moti - Lost [Radio Edit]\r\n95. Mike Hawkins &amp; 7 Skies - World On Fire [Radio Edit]\r\n96. Kshmr &amp; Marnik - Bazaar [Radio Edit]\r\n97. Psy - Daddy\r\n98. Italobrothers - Welcome To The Dancefloor\r\n99. Tujamo &amp; Danny Avila - Cream","torrent":{"xt":"urn:btih:ca3c810b293f51382b4bb58cbe9b2ea1f38866bb","amp;dn":"NRJ+Les+Hits+Du+Moment+December++2015","amp;tr":["udp%3A%2F%2Ftracker.leechers-paradise.org%3A6969","udp%3A%2F%2Fzer0day.ch%3A1337","udp%3A%2F%2Fopen.demonii.com%3A1337","udp%3A%2F%2Ftracker.coppersurfer.tk%3A6969","udp%3A%2F%2Fexodus.desync.com%3A6969"],"infoHash":"ca3c810b293f51382b4bb58cbe9b2ea1f38866bb","infoHashBuffer":{"type":"Buffer","data":[202,60,129,11,41,63,81,56,43,75,181,140,190,155,46,161,243,136,102,187]},"announce":[],"urlList":[]}}