{"title":"Yes - Tormato (1978)","uid":3810249,"size":110298226,"categoryP":"audio","categoryS":"music","magnet":"?xt=urn:btih:cae6cc805762342c54a4af877f647858286e708d&amp;dn=Yes+-+Tormato+%281978%29&amp;tr=udp%3A%2F%2Ftracker.openbittorrent.com%3A80&amp;tr=udp%3A%2F%2Fopen.demonii.com%3A1337&amp;tr=udp%3A%2F%2Ftracker.coppersurfer.tk%3A6969&amp;tr=udp%3A%2F%2Fexodus.desync.com%3A6969","seeders":1,"leechers":0,"uploader":"joannellis","files":18,"time":1190072716,"description":"ORIGINAL TRACK LISTING: (Atlantic, 1978)\n\n01 Future Times - Rejoice\n02 Don&amp;#039;t Kill the Whale\n03 Madrigal\n04 Release Release\n05 Arriving UFO\n06 Circus Of Heaven\n07 Onward\n08 On The Silent Wings Of Freedom\n\nBonus tracks (Rhino reissue, 2004)\n\n09 Abilene\n10 Money\n11 Picasso\n12 Some Are Born\n13 You Can Be Saved\n14 High\n15 Days\n16 Countryside\n17 Everybody&amp;#039;s Song\n18 Onward (Orchestral Version)\n\nYes Site: http://www.yesworld.com\nWiki article: http://en.wikipedia.org/wiki/Tormato\n\nPeace, enjoyment &amp; freedom to all.\n\n- J","torrent":{"xt":"urn:btih:cae6cc805762342c54a4af877f647858286e708d","amp;dn":"Yes+-+Tormato+%281978%29","amp;tr":["udp%3A%2F%2Ftracker.openbittorrent.com%3A80","udp%3A%2F%2Fopen.demonii.com%3A1337","udp%3A%2F%2Ftracker.coppersurfer.tk%3A6969","udp%3A%2F%2Fexodus.desync.com%3A6969"],"infoHash":"cae6cc805762342c54a4af877f647858286e708d","infoHashBuffer":{"type":"Buffer","data":[202,230,204,128,87,98,52,44,84,164,175,135,127,100,120,88,40,110,112,141]},"announce":[],"urlList":[]}}