{"title":"Rue - Thorns (2011) [mp3@320]","uid":6880463,"size":153972698,"categoryP":"audio","categoryS":"music","magnet":"?xt=urn:btih:d3f86b938f5d889d55ea85a84ce2e9c2344cfe0d&amp;dn=Rue+-+Thorns+%282011%29+%5Bmp3%40320%5D&amp;tr=udp%3A%2F%2Ftracker.openbittorrent.com%3A80&amp;tr=udp%3A%2F%2Fopen.demonii.com%3A1337&amp;tr=udp%3A%2F%2Ftracker.coppersurfer.tk%3A6969&amp;tr=udp%3A%2F%2Fexodus.desync.com%3A6969","seeders":1,"leechers":0,"uploader":"zibbik","files":14,"time":1323635913,"description":"BAnd: Rue\nAlbum: Thorns \nGenre: Sludge / Stoner Metal \nOrigin: United States\nFormat: 320 kbps\n\n1. Thorns (1:23) \n2. Brown (5:21) \n3. For Thousands Of Years (6:11) \n4. Sadaver (7:17) \n5. Broken Arms Broken Wings (6:04) \n6. Storm &amp; Sea (5:30) \n7. Pressures (4:49) \n8. Choice (4:31) \n9. Strong Will Evolve (5:04) \n10. High Iron Blues (5:01) \n11. Everfailure (3:27) \n12. A Walk Of Lies (6:21) \n13. Thorns (Reprise) (2:59)\n\nJeff-vox\nBurns-Guitars\nGreg-Drums\n","torrent":{"xt":"urn:btih:d3f86b938f5d889d55ea85a84ce2e9c2344cfe0d","amp;dn":"Rue+-+Thorns+%282011%29+%5Bmp3%40320%5D","amp;tr":["udp%3A%2F%2Ftracker.openbittorrent.com%3A80","udp%3A%2F%2Fopen.demonii.com%3A1337","udp%3A%2F%2Ftracker.coppersurfer.tk%3A6969","udp%3A%2F%2Fexodus.desync.com%3A6969"],"infoHash":"d3f86b938f5d889d55ea85a84ce2e9c2344cfe0d","infoHashBuffer":{"type":"Buffer","data":[211,248,107,147,143,93,136,157,85,234,133,168,76,226,233,194,52,76,254,13]},"announce":[],"urlList":[]}}