{"title":"American Horror Story S02E11 HDTV NL Subs DutchReleaseTeam","uid":8014541,"size":390322493,"categoryP":"video","categoryS":"tv_shows","magnet":"?xt=urn:btih:d879030f119755744ee8d6b41c1bf8de2e0f9375&amp;dn=American+Horror+Story+S02E11+HDTV+NL+Subs+DutchReleaseTeam&amp;tr=udp%3A%2F%2Ftracker.openbittorrent.com%3A80&amp;tr=udp%3A%2F%2Fopen.demonii.com%3A1337&amp;tr=udp%3A%2F%2Ftracker.coppersurfer.tk%3A6969&amp;tr=udp%3A%2F%2Fexodus.desync.com%3A6969","seeders":1,"leechers":0,"uploader":"Boobin16","files":-1,"time":1358036686,"description":"lot:\n\n American Horror Story: Asylum draait rond een criminele psychiatrische instelling en vindt plaats aan de Oostkust in het jaar 1964. \n Asylum verwijst enerzijds naar de voormalige tuberculose-afdeling die onder leiding van de katholieke kerk werd omgebouwd tot een psychiatrische instelling. \n Anderzijds verwijst de ondertitel ook naar het toevluchtsoord voor de ongewensten en de \n ongeliefden. \n Centraal in het verhaal staat de geestelijke gezondheid en de levensechte horror van de bewoners. \n\n\n Vertaling: Tokke\n\n\n Seizoen 2 Aflevering 11: Split Milk\n\n Grace tells Kit devastating news about the aliens' experiments on Alma; Dr. Thredson receives an unexpected visitor; the Monsignor goes to extreme lengths to silence Jude.\n\n\n Deze serie wordt u aangeboden door het DutchReleaseTeam.\n Voor de reviews van de nieuwste films, muziek, series, games etc\n Kom eens langs op   &lt;a href=&quot; http://www.hetmultimediacafe.be/&quot; rel=&quot;nofollow&quot; target=&quot;_NEW&quot;&gt; http://www.hetmultimediacafe.be/&lt;/a&gt;\n\n DutchReleaseteam = Hardcoded Dutch Subs","torrent":{"xt":"urn:btih:d879030f119755744ee8d6b41c1bf8de2e0f9375","amp;dn":"American+Horror+Story+S02E11+HDTV+NL+Subs+DutchReleaseTeam","amp;tr":["udp%3A%2F%2Ftracker.openbittorrent.com%3A80","udp%3A%2F%2Fopen.demonii.com%3A1337","udp%3A%2F%2Ftracker.coppersurfer.tk%3A6969","udp%3A%2F%2Fexodus.desync.com%3A6969"],"infoHash":"d879030f119755744ee8d6b41c1bf8de2e0f9375","infoHashBuffer":{"type":"Buffer","data":[216,121,3,15,17,151,85,116,78,232,214,180,28,27,248,222,46,15,147,117]},"announce":[],"urlList":[]}}