{"title":"Roni Size &amp; Reprazent - New Forms UK Release","uid":4024272,"size":150772196,"categoryP":"audio","categoryS":"music","magnet":"?xt=urn:btih:e66403619cd669e24bb5e94196323c45e0a31117&amp;dn=Roni+Size+%26+Reprazent+-+New+Forms+UK+Release&amp;tr=udp%3A%2F%2Ftracker.openbittorrent.com%3A80&amp;tr=udp%3A%2F%2Fopen.demonii.com%3A1337&amp;tr=udp%3A%2F%2Ftracker.coppersurfer.tk%3A6969&amp;tr=udp%3A%2F%2Fexodus.desync.com%3A6969","seeders":1,"leechers":0,"uploader":"mid_alex","files":14,"time":1202834886,"description":"New Forms is a 1997 album by the drum and bass act, Roni Size/Reprazent. It was the winner of the Mercury Music Prize in 1997,[1] and often cited as their magnum opus.[2] This album went 5 times platinum.\n\n\n[edit] Track listing\nThe original UK version features only disc one[3], with the US release featuring extra content on the second disc.[4]\n\n\n[edit] Disc one\n&quot;Railing&quot; ? 2:05 \n&quot;Brown Paper Bag&quot; ? 9:03 \n&quot;New Forms&quot; ? 7:45 \n&quot;Lets Get It On&quot; ? 6:57 \n&quot;Digital&quot; ? 9:05 \n&quot;Matter of Fact&quot; ? 4:05 \n&quot;Mad Cat&quot; ? 4:56 \n&quot;Heroes&quot; ? 6:35 \n&quot;Share the Fall Full Vocal Mix&quot; ? 6:13 \n&quot;Watching Windows&quot; ? 5:33 \n&quot;Beatbox&quot; ? 1:09 \n&quot;Morse Code&quot; ? 6:58 \n&quot;Destination&quot; ? 8:12 \n\n[edit] Disc two\n&quot;Intro&quot; ? 0:54 \n&quot;Hi-potent&quot; ? 6:53 \n&quot;Trust Me&quot; ? 6:26 \n&quot;Change My Life&quot; ? 8:27 \n&quot;Share The Fall&quot; ? 6:26 \n&quot;Down&quot; ? 6:51 \n&quot;Jazz&quot; ? 6:04 \n&quot;Hot Stuff&quot; ? 6:32 \n&quot;Ballet Dance&quot; ? 6:41 \n&quot;Electricks&quot; ? 6:17 \n\n\nMP3 @ 256KBPS\n\nUnfortunatly this is only disc one.","torrent":{"xt":"urn:btih:e66403619cd669e24bb5e94196323c45e0a31117","amp;dn":"Roni+Size+%26+Reprazent+-+New+Forms+UK+Release","amp;tr":["udp%3A%2F%2Ftracker.openbittorrent.com%3A80","udp%3A%2F%2Fopen.demonii.com%3A1337","udp%3A%2F%2Ftracker.coppersurfer.tk%3A6969","udp%3A%2F%2Fexodus.desync.com%3A6969"],"infoHash":"e66403619cd669e24bb5e94196323c45e0a31117","infoHashBuffer":{"type":"Buffer","data":[230,100,3,97,156,214,105,226,75,181,233,65,150,50,60,69,224,163,17,23]},"announce":[],"urlList":[]}}