{"title":"Lody Kong - Dreams And Visions  2016 320ak","uid":14160083,"size":87993149,"categoryP":"audio","categoryS":"music","magnet":"?xt=urn:btih:e73bb5f6f7203eee82c7b1bc9bce70a1bb605783&amp;dn=Lody+Kong+-+Dreams+And+Visions++2016+320ak&amp;tr=udp%3A%2F%2Ftracker.leechers-paradise.org%3A6969&amp;tr=udp%3A%2F%2Fzer0day.ch%3A1337&amp;tr=udp%3A%2F%2Fopen.demonii.com%3A1337&amp;tr=udp%3A%2F%2Ftracker.coppersurfer.tk%3A6969&amp;tr=udp%3A%2F%2Fexodus.desync.com%3A6969","seeders":1,"leechers":0,"uploader":"analogkid6103","files":12,"time":1459709528,"description":"Lody Kong - Dreams And Visions  2016 320ak\r\n\r\n&quot;Lody Kong is an American sludge metal band from Phoenix, Arizona, formed in 2011. The band is known for being led by brothers Igor and Zyon Cavalera, both sons of Soulfly frontman Max Cavalera.&quot;\r\n\r\nYear:\t2016\r\nStyle:\tSludge Metal\r\nAdditional:\tHardcore\r\nCountry:\tUSA\r\nFormat:\t320 mp3\r\nSize:\t83.92 MB\r\n\r\n\t\r\nAdded:\t03/04/2016 \r\n\r\nFiles:\t12\r\n\r\nDescription:\t\r\n\r\nLength : 0:32:37\r\n\r\nTracks :\r\n\r\n01. Chillin’, Killin’\r\n02. Dreams And Visions\r\n03. Kreative Center\r\n04. Pig In The Pen\r\n05. Rumsfield\r\n06. Smashed And Blasted\r\n07. Some Pulp\r\n08. The Dangerous Quest\r\n09. Topaz\r\n10. Venomous Kool-Aid","torrent":{"xt":"urn:btih:e73bb5f6f7203eee82c7b1bc9bce70a1bb605783","amp;dn":"Lody+Kong+-+Dreams+And+Visions++2016+320ak","amp;tr":["udp%3A%2F%2Ftracker.leechers-paradise.org%3A6969","udp%3A%2F%2Fzer0day.ch%3A1337","udp%3A%2F%2Fopen.demonii.com%3A1337","udp%3A%2F%2Ftracker.coppersurfer.tk%3A6969","udp%3A%2F%2Fexodus.desync.com%3A6969"],"infoHash":"e73bb5f6f7203eee82c7b1bc9bce70a1bb605783","infoHashBuffer":{"type":"Buffer","data":[231,59,181,246,247,32,62,238,130,199,177,188,155,206,112,161,187,96,87,131]},"announce":[],"urlList":[]}}